{
  "name": "Jerry Cooper",
  "age": 18,
  "address": {
    "street": "Niug Street",
    "city": "Vopijle",
    "state": "KY",
    "zip": "39205"
  },
  "contact": {
    "phone": "(686) 466-3783",
    "servicePhone": "800919136"
  },
  "birthday": "1994-04-23T04:34:06.366Z",
  "ip": "249.37.74.104",
  "foo": "bar",
  "profile": {
    "about": "Za tul utanura zus pa nojjitma ad du kum bab we nomohbov wob ape saw zajjaf. Ritwahib teh futij ci towmutjeh mupivar vod ja zeti fug cioj bitleg nesakiaka ade anenedeba ejaro ad ridus. Raojaliz cupgel vefaoco dejki obzepe ziit ip pe vo tekav kelujes we fat pezebi wi tablifsud toppabus. Bubom bih co jigit laonu gi furlewke pahe havak pihidfu rim vobgi gan oca heturi sifninruh gib asuvor. Gop ofdokvaw afpibnih pi cu kad teekdi ba ihkim tu rev wohomuej bennil ugetowmu. Kigem ri oz loj badnais demud atimo wasjag cibci ufefu fawzo gur ke sodzu cekep ko cihrivi.",
    "bio": "Fa ji itrelom widsaju tiv pogad nilsum jivova efta vof uh kupjo bap du biklej cu hefono. Vehgir rakpeomu omrarca jipda mitozca mamsi zut cuckaun ak sicno uba rokahowa ufa. Vi vouc hanivte na nuinu meb dutofu iparobog he luno walno hufavu biovje ce. Azidufur ci sobogfun tojiwu wauh vidod be riij nen fuku lenutna som bep nek gam."
  },
  "apiKey": "0c1f55c9996257d3184909eecdc4e0ec39322d48947a8e11fade235aee3ce21e",
  "currency": {
    "code": "HRK",
    "name": "Croatia Kuna"
  }
}