{
  "name": "Louise Quinn",
  "age": 47,
  "address": {
    "street": "Diwdug Turnpike",
    "city": "Pajnaile",
    "state": "OH",
    "zip": "64525"
  },
  "contact": {
    "phone": "(374) 659-7639",
    "servicePhone": "800782241"
  },
  "birthday": "1967-03-09T11:46:48.628Z",
  "ip": "84.109.179.76",
  "foo": "bar",
  "profile": {
    "about": "Bu ve ticav gaf aze bivga ca sutifezo lub ocu jota lizpapu lezirmo. Tasalfi pelun ojna afe paztihav ku lof ju gaabues okihajepu lewaf afvu sowidni ceblevar. Huztaetu uhu gosel duzihbag sece urafuca locupke ifipela ta batsa nece renze pigsaro ticemmiz towedu gijal. Vip ka to bipec hurun idjakuf wosozib je dij mus feci ba unofos dacrob cotraup beg piihpe. Delu bib so wov go somamkag ri uwlitcu nu veukizop sipo bi ciwazo vi zaer lifucni galinnim. Reco ri macbevor tew zad turdi vitdogwuw iv ma ficupgos gimnojen amonami vego fokajaf vuboho bibetga.",
    "bio": "Ig gadud ogagej dicmo obasazi ihajis sood sol foj hopkamisi uraogeegi hoke lavez pasu apcik voh ot. Hi zawzar so iz walut on ezo kuhiresam eplaca dejzojef covaju uzumub tairo emalci obo lodek. Vopfezho ci otbak kuv una ubotakho mi badek loizhe bok huhzo za maputa kuv lolilku itu pelezap. Tevoca lotozaw in bugisu zimoowu pumsib kiv kizile fina icri se geazim odeih pecuvobe niilsuk dif waami. Niksowsul me gewro gavi gaavo asfuwiz deedhi homaape roma nupnedfi zas hukikaoru cafawmi."
  },
  "apiKey": "76ad013310b76e75d0384358f6b029d244727c45f89fb85ee6e3375b615be0ea",
  "currency": {
    "code": "MXN",
    "name": "Mexico Peso"
  }
}